backend/__init__.py
backend/files.py
backend/git.py
backend/main.py
backend/rendering.py
backend/tmux.py
backend/services/__init__.py
backend/services/git_diff_service.py
frontend/app.js
frontend/favicon.png
frontend/favicon.svg
frontend/index.html
frontend/manifest.json
frontend/styles.css
frontend/sw.js
vibe_reader-0.1.10.dist-info/METADATA
vibe_reader-0.1.10.dist-info/WHEEL
vibe_reader-0.1.10.dist-info/entry_points.txt
vibe_reader-0.1.10.dist-info/RECORD
