Metadata-Version: 2.4
Name: vibe-reader
Version: 0.1.10
Summary: Add your description here
Author-email: PsychArch <PsychArch@github.com>
Requires-Python: >=3.13
Requires-Dist: dulwich==1.0.0
Requires-Dist: fastapi==0.128.0
Requires-Dist: libtmux==0.53.0
Requires-Dist: markdown==3.10
Requires-Dist: pydantic==2.12.5
Requires-Dist: pygments==2.19.2
Requires-Dist: uvicorn==0.40.0
Provides-Extra: dev
Requires-Dist: httpx==0.28.1; extra == 'dev'
Requires-Dist: pytest==9.0.2; extra == 'dev'
